downitall/__main__.py
downitall/core.py
downitall/resources/__init__.py
downitall/resources/animesources.py
downitall/resources/booksources.py
downitall/resources/mangasources.py
downitall/resources/musicsources.py
downitall/resources/streamsources.py
downitall/resources/tvsources.py
downitall_android-1.1.data/scripts/downitall
downitall_android-1.1.dist-info/licenses/LICENSE.txt
downitall_android-1.1.dist-info/METADATA
downitall_android-1.1.dist-info/WHEEL
downitall_android-1.1.dist-info/top_level.txt
downitall_android-1.1.dist-info/RECORD
