Metadata-Version: 2.4
Name: downitall_android
Version: 1.1
Summary: A cli to download and stream all kind of media
Author: Behram Akhtar/Aatiho Nora
Author-email: behramakhtar@gmail.com
License-File: LICENSE.txt
Requires-Dist: requests==2.32.4
Requires-Dist: bs4==0.0.2
Requires-Dist: selenium==4.9.1
Requires-Dist: selenium-wire==5.1.0
Requires-Dist: blinker==1.7.0
Requires-Dist: cbz-generator==1.0.0
Requires-Dist: tqdm==4.67.1
Requires-Dist: gdown==5.2.0
Requires-Dist: term-image==0.7.2
Requires-Dist: questionary==2.1.0
Requires-Dist: ytmusicapi==1.10.3
Requires-Dist: xdcc-dl==5.2.1
Requires-Dist: streamlink==7.5.0
Requires-Dist: m3u-ipytv==0.2.11
Dynamic: author
Dynamic: author-email
Dynamic: description
Dynamic: description-content-type
Dynamic: license-file
Dynamic: requires-dist
Dynamic: summary
